setup.cfg
setup.py
fwdocker/__init__.py
fwdocker/__main__.py
fwdocker/backup.py
fwdocker/dc-allin1-data-volume.yml
fwdocker/dc-allin1-mapped.yml
fwdocker/dc-allin1-mapped2.yml
fwdocker/fwdocker.py
fwdocker/server.py
fwdocker.egg-info/PKG-INFO
fwdocker.egg-info/SOURCES.txt
fwdocker.egg-info/dependency_links.txt
fwdocker.egg-info/entry_points.txt
fwdocker.egg-info/requires.txt
fwdocker.egg-info/top_level.txt