Metadata-Version: 1.1
Name: fwdocker
Version: 0.4.6
Summary: A wrapper/utility to make it easy to use FileWave with Docker
Home-page: https://github.com/fw-dev/fwdocker
Author: John Clayton
Author-email: johnc@filewave.com
License: Apache
Download-URL: https://github.com/johncclayton/fwdocker/tarball/0.1
Keywords: filewave,docker,mdm,distribution
Platform: UNKNOWN
